pyavd/LICENSE
pyavd/__init__.py
pyavd/avd_schema_tools.py
pyavd/constants.py
pyavd/get_avd_facts.py
pyavd/get_device_config.py
pyavd/get_device_doc.py
pyavd/get_device_structured_config.py
pyavd/get_device_test_catalog.py
pyavd/get_fabric_documentation.py
pyavd/templater.py
pyavd/validate_inputs.py
pyavd/validate_structured_config.py
pyavd/validation_result.py
pyavd/_anta/__init__.py
pyavd/_anta/constants.py
pyavd/_anta/factories.py
pyavd/_anta/index.py
pyavd/_anta/logs.py
pyavd/_anta/models.py
pyavd/_anta/utils.py
pyavd/_anta/input_factories/__init__.py
pyavd/_anta/input_factories/_base_classes.py
pyavd/_anta/input_factories/avt.py
pyavd/_anta/input_factories/connectivity.py
pyavd/_anta/input_factories/hardware.py
pyavd/_anta/input_factories/interfaces.py
pyavd/_anta/input_factories/router_path_selection.py
pyavd/_anta/input_factories/routing_bgp.py
pyavd/_anta/input_factories/routing_generic.py
pyavd/_anta/input_factories/security.py
pyavd/_anta/input_factories/system.py
pyavd/_anta/lib/__init__.py
pyavd/_anta/lib/tests/__init__.py
pyavd/_cv/__init__.py
pyavd/_cv/api/__init__.py
pyavd/_cv/api/arista/__init__.py
pyavd/_cv/api/arista/alert/__init__.py
pyavd/_cv/api/arista/alert/v1/__init__.py
pyavd/_cv/api/arista/bugexposure/__init__.py
pyavd/_cv/api/arista/bugexposure/v1/__init__.py
pyavd/_cv/api/arista/changecontrol/__init__.py
pyavd/_cv/api/arista/changecontrol/v1/__init__.py
pyavd/_cv/api/arista/configlet/__init__.py
pyavd/_cv/api/arista/configlet/v1/__init__.py
pyavd/_cv/api/arista/configstatus/__init__.py
pyavd/_cv/api/arista/configstatus/v1/__init__.py
pyavd/_cv/api/arista/connectivitymonitor/__init__.py
pyavd/_cv/api/arista/connectivitymonitor/v1/__init__.py
pyavd/_cv/api/arista/dashboard/__init__.py
pyavd/_cv/api/arista/dashboard/v1/__init__.py
pyavd/_cv/api/arista/endpointlocation/__init__.py
pyavd/_cv/api/arista/endpointlocation/v1/__init__.py
pyavd/_cv/api/arista/event/__init__.py
pyavd/_cv/api/arista/event/v1/__init__.py
pyavd-5.7.1.dist-info/METADATA
pyavd-5.7.1.dist-info/WHEEL
pyavd-5.7.1.dist-info/top_level.txt
pyavd-5.7.1.dist-info/RECORD
