Metadata-Version: 2.4
Name: pyavd
Version: 5.7.1
Summary: Arista AVD
Author-email: Arista Networks <ansible@arista.com>
License:                                  Apache License
Project-URL: homepage, https://avd.arista.com
Project-URL: repository, https://github.com/aristanetworks/avd
Keywords: pyavd
Classifier: Operating System :: OS Independent
Classifier: Development Status :: 5 - Production/Stable
Classifier: Intended Audience :: Developers
Classifier: Programming Language :: Python
Classifier: Programming Language :: Python :: 3.10
Classifier: Programming Language :: Python :: 3.11
Classifier: Programming Language :: Python :: 3.12
Classifier: Programming Language :: Python :: 3.13
Classifier: Topic :: Software Development :: Libraries :: Python Modules
Classifier: Topic :: Software Development :: Testing
Requires-Python: >=3.10
Requires-Dist: aristaproto>=0.1.1
Requires-Dist: cryptography>=38.0.4
Requires-Dist: deepmerge>=1.1.0
Requires-Dist: Jinja2>=3.0
Requires-Dist: PyYAML>=6.0.0
Requires-Dist: requests>=2.27.0
Provides-Extra: ansible
Requires-Dist: ansible-core<2.19.0,>=2.16.0; extra == "ansible"
Requires-Dist: pyavd[ansible-collection]; extra == "ansible"
Provides-Extra: ansible-collection
Requires-Dist: anta>=1.6.0; extra == "ansible-collection"
Requires-Dist: cvprac>=1.4.0; extra == "ansible-collection"
Requires-Dist: netaddr>=0.7.19; extra == "ansible-collection"
Requires-Dist: treelib>=1.5.5; extra == "ansible-collection"
Requires-Dist: jsonschema>=3.2.0; extra == "ansible-collection"
Requires-Dist: distlib>=0.3.9; extra == "ansible-collection"
